{
  "date": "20251201",
  "trades": [
    {
      "ts_code": "159807.SZ",
      "action": "BUY",
      "shares": 71300,
      "price": 0.701,
      "amount": -49991.296259999996,
      "commission": 4.99813,
      "date": "2025-12-01",
      "reason": "KAMA持续确认买入信号（n=0）！价格上穿KAMA"
    },
    {
      "ts_code": "159996.SZ",
      "action": "BUY",
      "shares": 33000,
      "price": 1.512,
      "amount": -49905.9792,
      "commission": 4.9896,
      "date": "2025-12-01",
      "reason": "KAMA持续确认买入信号（n=0）！价格上穿KAMA"
    },
    {
      "ts_code": "159845.SZ",
      "action": "BUY",
      "shares": 16400,
      "price": 3.039,
      "amount": -49849.56792,
      "commission": 4.983960000000001,
      "date": "2025-12-01",
      "reason": "KAMA持续确认买入信号（n=0）！价格上穿KAMA"
    },
    {
      "ts_code": "159766.SZ",
      "action": "BUY",
      "shares": 64500,
      "price": 0.775,
      "amount": -49997.4975,
      "commission": 4.99875,
      "date": "2025-12-01",
      "reason": "KAMA持续确认买入信号（n=0）！价格上穿KAMA"
    }
  ],
  "trade_count": 4,
  "timestamp": "2025-12-01 19:01:28",
  "execution_time": "2025-12-01T19:01:28.103039",
  "execution_context": {
    "status": "executed",
    "strategy": "kama_cross",
    "sell_count": 0,
    "buy_count": 4,
    "forced": false
  }
}